{
  "name": "Which DIY Connoisseur are You? ",
  "questions": [
    {
      "question": "Choose your favourite group of villagers amongst the following groups",
      "answers": [
        {
          "type": "All Rounder",
          "content": "Down-to-earth types like Flurry, Maple and Pate who are steady and comforting"
        },
        {
          "type": "Expert",
          "content": "NPC’s like Blanca, Celeste and Sahara who bring a unique flair to the game"
        },
        {
          "type": "Customiser",
          "content": "Tom Nook, Reese and Cyrus, Cyrus because they provide players with customisation options for home and specialty items"
        },
        {
          "type": "Aspiring",
          "content": "Cute villagers that remind you of food like Chai, Chrissy and Marshal"
        }
      ]
    },
    {
      "question": "Have you downloaded the recent Happy Home Paradise DLC?",
      "answers": [
        {
          "type": "All Rounder",
          "content": "Sure did! I couldn’t wait to explore new items"
        },
        {
          "type": "Expert",
          "content": "I did because I was excited about the prospect of different seasons for vacation homes within the archipelago"
        },
        {
          "type": "Customiser",
          "content": "Yes because I was curious to see what items and customisations I could create for villagers"
        },
        {
          "type": "Aspiring",
          "content": "I’ll get to it sometime"
        }
      ]
    },
    {
      "question": "3. How do you feel about the weekly Happy Home Academy assessments?",
      "answers": [
        {
          "type": "All Rounder",
          "content": "  1. I’m relaxed about it because I’m pretty handy with decorating my house"
        },
        {
          "type": "Expert",
          "content": "I get excited about displaying seasonal items I crafted"
        },
        {
          "type": "Customiser",
          "content": "I look forward to confidently displaying customisations of items"
        },
        {
          "type": "Aspiring",
          "content": "So-so, it would be nice if food items from cooking and baking got more points!"
        }
      ]
    },
    {
      "question": "4. Do you have an area on your island dedicated to farming?",
      "answers": [
        {
          "type": "All Rounder",
          "content": "I have a big fruit orchard  with a few other basic crops like pumpkins and wheat"
        },
        {
          "type": "Expert",
          "content": "I farm according to in-game seasons, like growing pumpkins for Halloween"
        },
        {
          "type": "Customiser",
          "content": "I focus more on trading items that I can later customise myself"
        },
        {
          "type": "Aspiring",
          "content": "I have extensive farmlands with a variety of crops for making cooking ingredients"
        }
      ]
    },
    {
      "question": "Do you have a designated DIY set-up on your island?",
      "answers": [
        {
          "type": "All Rounder",
          "content": "I do, because my friends often visit my island so that I can craft items for them"
        },
        {
          "type": "Expert",
          "content": "My DIY bench ‘floats’ around my island depending on the time of year"
        },
        {
          "type": "Customiser",
          "content": "  3. I have a DIY area in my house with lots of customisation kits on hand"
        },
        {
          "type": "Aspiring",
          "content": "The kitchen is my studio where I get to make culinary recipes"
        }
      ]
    },
    {
      "question": "Do you have a collection of materials for DIY’s?",
      "answers": [
        {
          "type": "All Rounder",
          "content": "I have a bit of everything on hand"
        },
        {
          "type": "Expert",
          "content": "I like to stow away seasonal materials like cherry blossom petals, mushrooms and shells"
        },
        {
          "type": "Customiser",
          "content": "I can’t say that I do"
        },
        {
          "type": "Aspiring",
          "content": "My storage s filled with harvested food items like bamboo, carrots and sugar bags"
        }
      ]
    }
  ],
  "results": {
    "All Rounder": "You are a DIY all rounder who’s always prepared for a project!",
    "Expert": "You are an expert in collecting seasonal materials for seasonal DIY’s!",
    "Customiser": "You are a Customiser who has every gyroid in every colour!",
    "Aspiring": "You are constantly expanding your Cooking and Baking DIY repertoire!"
  },
  "hasImages": true
}
